django_api_view/__init__.py
django_api_view/admin.py
django_api_view/api_response.py
django_api_view/api_view.py
django_api_view/apps.py
django_api_view/models.py
django_api_view-0.1.1.dist-info/DESCRIPTION.rst
django_api_view-0.1.1.dist-info/LICENSE.txt
django_api_view-0.1.1.dist-info/METADATA
django_api_view-0.1.1.dist-info/RECORD
django_api_view-0.1.1.dist-info/WHEEL
django_api_view-0.1.1.dist-info/metadata.json
django_api_view-0.1.1.dist-info/top_level.txt
