Metadata-Version: 2.0
Name: django-api-view
Version: 0.1.1
Summary: Django api view
Home-page: https://github.com/anthon-alindada/django_api_view
Author: Anthon Alindada
Author-email: anthon.alindada.435@gmail.com
License: MIT
Keywords: django api view
Platform: UNKNOWN
Classifier: Development Status :: 3 - Alpha
Classifier: Framework :: Django
Classifier: Framework :: Django :: 1.10
Classifier: Intended Audience :: Developers
Classifier: License :: OSI Approved :: BSD License
Classifier: Natural Language :: English
Classifier: Programming Language :: Python :: 2
Classifier: Programming Language :: Python :: 2.7
Classifier: Programming Language :: Python :: 3
Classifier: Programming Language :: Python :: 3.4
Classifier: Programming Language :: Python :: 3.5
Requires-Dist: Django (>=1.8)
